hello_utils/__init__.py
hello_utils/greetings.py
hello_utils-0.1.0.dist-info/METADATA
hello_utils-0.1.0.dist-info/WHEEL
hello_utils-0.1.0.dist-info/top_level.txt
hello_utils-0.1.0.dist-info/RECORD
