Metadata-Version: 2.4
Name: hello-utils
Version: 0.1.0
Summary: A simple hello world utility package
Home-page: https://github.com/yourusername/hello-utils
Author: Your Name
Author-email: you@example.com
Classifier: Programming Language :: Python :: 3
Classifier: License :: OSI Approved :: MIT License
Requires-Python: >=3.7
Dynamic: author
Dynamic: author-email
Dynamic: classifier
Dynamic: description-content-type
Dynamic: home-page
Dynamic: requires-python
Dynamic: summary
